img_to_pdf_compress/__init__.py
img_to_pdf_compress/main.py
img_to_pdf_compress-4.0.0.dist-info/METADATA
img_to_pdf_compress-4.0.0.dist-info/WHEEL
img_to_pdf_compress-4.0.0.dist-info/entry_points.txt
img_to_pdf_compress-4.0.0.dist-info/licenses/LICENSE
img_to_pdf_compress-4.0.0.dist-info/RECORD
