Metadata-Version: 2.4
Name: img-to-pdf-compress
Version: 4.0.0
Summary: Convert JPG/PNG images to compressed PDF
Author-email: Frambudi <your@email.com>
License: This is free and unencumbered software released into the public domain.
License-File: LICENSE
Requires-Python: >=3.8
Requires-Dist: img2pdf
Requires-Dist: pillow
